synthetic_gymnax/__init__.py
synthetic_gymnax/synthenv_network.py
synthetic_gymnax/synthetic_environment.py
synthetic_gymnax/checkpoints/acrobot/checkpoint.pkl
synthetic_gymnax/checkpoints/cartpole/checkpoint.pkl
synthetic_gymnax/checkpoints/continuous_mountaincar/checkpoint.pkl
synthetic_gymnax/checkpoints/halfcheetah/checkpoint.pkl
synthetic_gymnax/checkpoints/hopper/checkpoint.pkl
synthetic_gymnax/checkpoints/humanoidstandup/checkpoint.pkl
synthetic_gymnax/checkpoints/mountaincar/checkpoint.pkl
synthetic_gymnax/checkpoints/pendulum/checkpoint.pkl
synthetic_gymnax/checkpoints/swimmer/checkpoint.pkl
synthetic_gymnax/checkpoints/walker2d/checkpoint.pkl
test/__init__.py
test/test_environments.py
synthetic_gymnax-0.0.1.dist-info/METADATA
synthetic_gymnax-0.0.1.dist-info/WHEEL
synthetic_gymnax-0.0.1.dist-info/top_level.txt
synthetic_gymnax-0.0.1.dist-info/RECORD
