Metadata-Version: 2.1
Name: synthetic-gymnax
Version: 0.0.1
Summary: Synthetic gymnax environments
Home-page: https://github.com/keraJLi/synthetic-gymnax
Author: Jarek Liesen
Requires-Dist: chex
Requires-Dist: gymnax
Requires-Dist: brax
Requires-Dist: flax
Requires-Dist: distrax
Requires-Dist: rejax
